[
  {
    "id": 5,
    "name": "Burkar med sockervadd",
    "price": 25.0,
    "image": "Burkar med sockervadd_1746308833.jpg",
    "stands": [
      "G",
      "I"
    ]
  },
  {
    "id": 6,
    "name": "Hamburgare",
    "price": 60.0,
    "image": "Hamburgare_1746295394.jpg",
    "stands": [
      "J"
    ]
  },
  {
    "id": 7,
    "name": "popcorn",
    "price": 30.0,
    "image": "popcorn_1746295417.jpg",
    "stands": "K"
  },
  {
    "id": 8,
    "name": "Våffla",
    "price": 35.0,
    "image": "våfflor_1746298409.jpg",
    "stands": "F"
  },
  {
    "id": 9,
    "name": "Kaffe&Te",
    "price": 20.0,
    "image": "kaffe_1746298506.JPG",
    "stands": [
      "F",
      "J"
    ]
  },
  {
    "id": 11,
    "name": "Spritspåsar med popcorn",
    "price": 20.0,
    "image": "popcorn_1746299007.jpg",
    "stands": "I"
  },
  {
    "id": 15,
    "name": "Hotsnacks-påsar",
    "price": 20.0,
    "image": "hotsnacks_1746299598.png",
    "stands": "K"
  },
  {
    "id": 16,
    "name": "Strutar",
    "price": 25.0,
    "stands": "G",
    "image": "Strutar_1746308824.jpg"
  },
  {
    "id": 18,
    "name": "Läsk och vatten",
    "price": 20.0,
    "stands": [
      "F",
      "I",
      "J"
    ],
    "image": "Läsk_1746309131.jpg"
  },
  {
    "id": 20,
    "name": "Munk",
    "price": 15.0,
    "stands": "F",
    "image": "Munkar_1746309842.jpg"
  },
  {
    "id": 21,
    "name": "Korv",
    "price": 25.0,
    "stands": "J",
    "image": "Korv_1746310346.jpg"
  },
  {
    "id": 22,
    "name": "Linsgryta",
    "price": 25.0,
    "stands": "J",
    "image": "Linsgryta_1746310389.jpg"
  },
  {
    "id": 23,
    "name": "Toast",
    "price": 30.0,
    "stands": "J",
    "image": "Toast_1746310848.jpg"
  },
  {
    "id": 24,
    "name": "Småkakor i påse",
    "price": 30.0,
    "stands": [
      "J",
      "F"
    ],
    "image": "Småkakor i påse_1746310917.jpg"
  },
  {
    "id": 25,
    "name": "Brända mandlar",
    "price": 30.0,
    "stands": [
      "J",
      "F",
      "I"
    ],
    "image": "Brända mandlar_1746310946.jpg"
  },
  {
    "id": 26,
    "name": "Cocosboll",
    "price": 10.0,
    "stands": [
      "J",
      "F"
    ],
    "image": "Cocosboll_1746310987.jpg"
  },
  {
    "id": 29,
    "name": "Festis",
    "price": 15.0,
    "stands": [
      "J",
      "F",
      "I"
    ],
    "image": "Festis_1746311273.jpg"
  }
]